expt.cpython-38-darwin.so
pymrmre/MrmreData.py
pymrmre/MrmreFilter.py
pymrmre/__init__.py
pymrmre/constants.py
pymrmre/mrmr.py
pymrmre/expt/Data.cpp
pymrmre/expt/Data.h
pymrmre/expt/Filter.cpp
pymrmre/expt/Filter.h
pymrmre/expt/MathExtensions.cpp
pymrmre/expt/MathExtensions.h
pymrmre/expt/Matrix.cpp
pymrmre/expt/Matrix.h
pymrmre/expt/MutualInformationMatrix.cpp
pymrmre/expt/MutualInformationMatrix.h
pymrmre/expt/exports.cpp
pymrmre/expt/exports.h
pymrmre/expt/expt.cpp
pymrmre/expt/expt.pyx
pymrmre-1.0.7.dist-info/LICENSE
pymrmre-1.0.7.dist-info/METADATA
pymrmre-1.0.7.dist-info/WHEEL
pymrmre-1.0.7.dist-info/top_level.txt
pymrmre-1.0.7.dist-info/RECORD
