Metadata-Version: 2.1
Name: pymrmre
Version: 1.0.7
Summary: A Python package for Parallelized Minimum Redundancy, Maximum Relevance (mRMR) Ensemble Feature selections.
Home-page: https://github.com/bhklab/PymRMRe
Author: Bo Li, Benjamin Haibe-Kains
Author-email: benjamin.haibe.kains@utoronto.ca
License: MIT license
Keywords: pymrmre featureselection genomics computationalbiology
Platform: UNKNOWN
